proxy_abuyun/__init__.py
proxy_abuyun/proxy.py
proxy_abuyun-1.0.3.dist-info/LICENSE
proxy_abuyun-1.0.3.dist-info/METADATA
proxy_abuyun-1.0.3.dist-info/WHEEL
proxy_abuyun-1.0.3.dist-info/top_level.txt
proxy_abuyun-1.0.3.dist-info/RECORD
